carabiner/__init__.py
carabiner/cast.py
carabiner/cli.py
carabiner/cliutils.py
carabiner/collections.py
carabiner/decorators.py
carabiner/itertools.py
carabiner/random.py
carabiner/utils.py
carabiner/io/__init__.py
carabiner/io/utils.py
carabiner/mpl/__init__.py
carabiner/mpl/utils.py
carabiner/pd/__init__.py
carabiner/pd/utils.py
carabiner/tf/__init__.py
carabiner/tf/utils.py
carabiner_tools-0.0.4.dist-info/LICENSE
carabiner_tools-0.0.4.dist-info/METADATA
carabiner_tools-0.0.4.dist-info/WHEEL
carabiner_tools-0.0.4.dist-info/entry_points.txt
carabiner_tools-0.0.4.dist-info/top_level.txt
carabiner_tools-0.0.4.dist-info/RECORD
