Metadata-Version: 2.2
Name: carabiner-tools
Version: 0.0.4
Summary: Useful utilities.
Author-email: Eachan Johnson <eachan.johnson@crick.ac.uk>
License: MIT License
Project-URL: Homepage, https://github.com/scbirlab/carabiner
Project-URL: Bug Tracker, https://github.com/scbirlab/carabiner/issues
Keywords: bioinformatics,machine-learning,data
Classifier: Development Status :: 3 - Alpha
Classifier: Intended Audience :: Science/Research
Classifier: Topic :: Scientific/Engineering :: Bio-Informatics
Classifier: License :: OSI Approved :: MIT License
Classifier: Programming Language :: Python :: 3.8
Classifier: Programming Language :: Python :: 3.9
Classifier: Programming Language :: Python :: 3.10
Classifier: Programming Language :: Python :: 3.11
Classifier: Programming Language :: Python :: 3.12
Classifier: Programming Language :: Python :: 3 :: Only
Requires-Python: >=3.8
License-File: LICENSE
Requires-Dist: tqdm
Provides-Extra: deep
Requires-Dist: tensorflow; extra == "deep"
Provides-Extra: pd
Requires-Dist: pandas; extra == "pd"
Requires-Dist: openpyxl==3.1.0; extra == "pd"
Provides-Extra: mpl
Requires-Dist: carabiner-tools[pd]; extra == "mpl"
Requires-Dist: matplotlib; extra == "mpl"
Requires-Dist: numpy; extra == "mpl"
Provides-Extra: all
Requires-Dist: carabiner-tools[deep,mpl,pd]; extra == "all"
